airchief/__init__.py
airchief-0.0.2.dist-info/METADATA
airchief-0.0.2.dist-info/WHEEL
airchief-0.0.2.dist-info/licenses/LICENSE
airchief-0.0.2.dist-info/RECORD
