Metadata-Version: 2.4
Name: airchief
Version: 0.0.2
Summary: Namespace reservation - coming soon
Project-URL: Homepage, https://github.com/shaneholloman/airchief
Project-URL: Repository, https://github.com/shaneholloman/airchief
Author-email: Shane Holloman <shaneholloman@gmail.com>
License-Expression: MIT
License-File: LICENSE
Classifier: Development Status :: 1 - Planning
Classifier: Intended Audience :: Developers
Classifier: License :: OSI Approved :: MIT License
Classifier: Programming Language :: Python :: 3
Classifier: Programming Language :: Python :: 3.8
Classifier: Programming Language :: Python :: 3.9
Classifier: Programming Language :: Python :: 3.10
Classifier: Programming Language :: Python :: 3.11
Classifier: Programming Language :: Python :: 3.12
Requires-Python: >=3.8
